legal_segmenter/__init__.py
legal_segmenter/constants/__init__.py
legal_segmenter/constants/case_names.txt
legal_segmenter/constants/court_documents.txt
legal_segmenter/constants/court_names.txt
legal_segmenter/constants/geographical_terms.txt
legal_segmenter/constants/judges_and_officials.txt
legal_segmenter/constants/legislative_docs.txt
legal_segmenter/constants/months.txt
legal_segmenter/constants/periodicals.txt
legal_segmenter/constants/publishing_terms.txt
legal_segmenter/constants/services.txt
legal_segmenter/constants/subdivisions.txt
legal_segmenter/segmenter.py
legal_segmenter-0.1.2.dist-info/WHEEL
legal_segmenter-0.1.2.dist-info/METADATA
legal_segmenter-0.1.2.dist-info/RECORD
