Metadata-Version: 2.1
Name: legal-segmenter
Version: 0.1.2
Summary: A simple library for segmenting legal texts.
Home-page: https://github.com/neelguha/legal-segmenter
License: MIT
Author: Neel Guha
Author-email: nguha@cs.stanford.com
Requires-Python: >=3.8,<4.0
Classifier: License :: OSI Approved :: MIT License
Classifier: Programming Language :: Python :: 3
Classifier: Programming Language :: Python :: 3.10
Classifier: Programming Language :: Python :: 3.8
Classifier: Programming Language :: Python :: 3.9
Project-URL: Repository, https://github.com/neelguha/legal-segmenter
